{
  "mcpServers": {
    "awslabs.cloudwatch-mcp-server": {
      "command": "uvx",
      "args": [
        "awslabs.cloudwatch-mcp-server@latest"
      ],
      "env": {
        "AWS_PROFILE": "default",
        "AWS_REGION": "us-east-1",
        "FASTMCP_LOG_LEVEL": "ERROR"
      },
      "disabled": false,
      "autoApprove": []
    },
    "awslabs.cloudwatch-applicationsignals-mcp-server": {
      "command": "uvx",
      "args": [
        "awslabs.cloudwatch-applicationsignals-mcp-server@latest"
      ],
      "env": {
        "AWS_PROFILE": "default",
        "AWS_REGION": "us-east-1",
        "FASTMCP_LOG_LEVEL": "ERROR"
      },
      "disabled": false,
      "autoApprove": []
    },
    "awslabs.cloudtrail-mcp-server": {
      "autoApprove": [],
      "disabled": false,
      "command": "uvx",
      "args": [
        "awslabs.cloudtrail-mcp-server@latest"
      ],
      "env": {
        "AWS_PROFILE": "default",
        "AWS_REGION": "us-east-1",
        "FASTMCP_LOG_LEVEL": "ERROR"
      },
      "transportType": "stdio"
    },
    "awslabs.aws-documentation-mcp-server": {
      "command": "uvx",
      "args": [
        "awslabs.aws-documentation-mcp-server@latest"
      ],
      "env": {
        "FASTMCP_LOG_LEVEL": "ERROR"
      },
      "disabled": false,
      "autoApprove": []
    }
  }
}
